asphalt/__main__.py
asphalt/core/__init__.py
asphalt/core/cli.py
asphalt/core/component.py
asphalt/core/concurrent.py
asphalt/core/context.py
asphalt/core/event.py
asphalt/core/py.typed
asphalt/core/runner.py
asphalt/core/utils.py
asphalt-4.12.0.dist-info/LICENSE
asphalt-4.12.0.dist-info/METADATA
asphalt-4.12.0.dist-info/WHEEL
asphalt-4.12.0.dist-info/entry_points.txt
asphalt-4.12.0.dist-info/top_level.txt
asphalt-4.12.0.dist-info/RECORD
