Metadata-Version: 2.1
Name: asphalt
Version: 4.12.0
Summary: A microframework for network oriented applications
Author-email: Alex Grönholm <alex.gronholm@nextday.fi>
License: Apache License 2.0
Project-URL: Component projects, https://github.com/asphalt-framework
Project-URL: Documentation, https://asphalt.readthedocs.org/en/latest/
Project-URL: Help and support, https://github.com/asphalt-framework/asphalt/wiki/Help-and-support
Project-URL: Source code, https://github.com/asphalt-framework/asphalt
Project-URL: Issue tracker, https://github.com/asphalt-framework/asphalt/issues
Classifier: Development Status :: 5 - Production/Stable
Classifier: Intended Audience :: Developers
Classifier: License :: OSI Approved :: Apache Software License
Classifier: Topic :: Software Development :: Libraries :: Application Frameworks
Classifier: Framework :: AsyncIO
Classifier: Typing :: Typed
Classifier: Programming Language :: Python
Classifier: Programming Language :: Python :: 3 :: Only
Classifier: Programming Language :: Python :: 3.7
Classifier: Programming Language :: Python :: 3.8
Classifier: Programming Language :: Python :: 3.9
Classifier: Programming Language :: Python :: 3.10
Classifier: Programming Language :: Python :: 3.11
Classifier: Programming Language :: Python :: 3.12
Requires-Python: >=3.7
License-File: LICENSE
Requires-Dist: ruamel.yaml (>=0.15)
Requires-Dist: async-generator (~=1.4)
Requires-Dist: asyncio-extras (~=1.3)
Requires-Dist: async-timeout (>=2.0)
Requires-Dist: click (>=6.6)
Requires-Dist: importlib-metadata (>=4.4) ; python_version < "3.10"
Requires-Dist: typing-extensions ; python_version < "3.10"
Provides-Extra: doc
Requires-Dist: Sphinx (>=6.0) ; extra == 'doc'
Requires-Dist: sphinx-rtd-theme (>=1.2.0) ; extra == 'doc'
Requires-Dist: sphinx-autodoc-typehints (>=1.22) ; extra == 'doc'
Provides-Extra: test
Requires-Dist: pytest (>=3.9) ; extra == 'test'
Requires-Dist: pytest-asyncio ; extra == 'test'
Requires-Dist: pytest-cov ; extra == 'test'
Requires-Dist: uvloop ; (python_version < "3.12" and platform_python_implementation == "CPython" and platform_system != "Windows") and extra == 'test'
Provides-Extra: tokio
Requires-Dist: tokio ; extra == 'tokio'
Provides-Extra: uvloop
Requires-Dist: uvloop (>=0.4.10) ; extra == 'uvloop'
